[
    {
        "id": 70438222,
        "title": "O.K.",
        "isCover": false,
        "date": "2019-10-07 14:43",
        "rank": 1,
        "point": 241264,
        "view": 52816,
        "favorite": 6468,
        "reply": 664,
        "danmaku": 266,
        "corrA": 0.7,
        "corrB": 30.62
    },
    {
        "id": 70451110,
        "title": "今天唱起浏阳河",
        "isCover": false,
        "date": "2019-10-07 16:41",
        "rank": 2,
        "point": 184894,
        "view": 21939,
        "favorite": 3759,
        "reply": 504,
        "danmaku": 186,
        "corrA": 0.62,
        "corrB": 42.83
    },
    {
        "id": 69519887,
        "title": "地势坤",
        "isCover": false,
        "date": "2019-10-01 00:00",
        "rank": 3,
        "point": 138043,
        "view": 90146,
        "favorite": 5460,
        "reply": 228,
        "danmaku": 771,
        "corrA": 0.82,
        "corrB": 15.14
    },
    {
        "id": 69833043,
        "title": "雅俗共赏",
        "isCover": false,
        "date": "2019-10-03 10:00",
        "rank": 4,
        "point": 124018,
        "view": 30678,
        "favorite": 3529,
        "reply": 94,
        "danmaku": 106,
        "corrA": 0.89,
        "corrB": 28.76
    },
    {
        "id": 70263084,
        "title": "爱情婚姻争斗战",
        "isCover": true,
        "date": "2019-10-06 12:31",
        "rank": 5,
        "point": 99783,
        "view": 25114,
        "favorite": 2725,
        "reply": 549,
        "danmaku": 338,
        "corrA": 0.59,
        "corrB": 27.13
    },
    {
        "id": 67613570,
        "title": "你是瞬间",
        "isCover": false,
        "date": "2019-09-14 13:25",
        "rank": 6,
        "point": 84494,
        "view": 15301,
        "favorite": 2057,
        "reply": 130,
        "danmaku": 94,
        "corrA": 0.81,
        "corrB": 33.61
    },
    {
        "id": 69910651,
        "title": "七十载",
        "isCover": false,
        "date": "2019-10-03 21:45",
        "rank": 7,
        "point": 82543,
        "view": 48285,
        "favorite": 3112,
        "reply": 142,
        "danmaku": 205,
        "corrA": 0.87,
        "corrB": 16.11
    },
    {
        "id": 69770270,
        "title": "长安辞",
        "isCover": false,
        "date": "2019-10-07 12:00",
        "rank": 8,
        "point": 73333,
        "view": 6881,
        "favorite": 1325,
        "reply": 150,
        "danmaku": 60,
        "corrA": 0.7,
        "corrB": 48.14
    },
    {
        "id": 69919531,
        "title": "阿娇",
        "isCover": false,
        "date": "2019-10-03 18:35",
        "rank": 9,
        "point": 71295,
        "view": 7068,
        "favorite": 1334,
        "reply": 66,
        "danmaku": 303,
        "corrA": 0.66,
        "corrB": 47.18
    },
    {
        "id": 43426592,
        "title": "勾指起誓",
        "isCover": false,
        "date": "2019-02-13 22:09",
        "rank": 10,
        "point": 68420,
        "view": 38766,
        "favorite": 1448,
        "reply": 18347,
        "danmaku": 212,
        "corrA": 0.07,
        "corrB": 9.34
    },
    {
        "id": 56836021,
        "title": "再一杯！",
        "isCover": false,
        "date": "2019-06-26 18:25",
        "rank": 11,
        "point": 57021,
        "view": 16973,
        "favorite": 1709,
        "reply": 18,
        "danmaku": 121,
        "corrA": 0.91,
        "corrB": 25.17
    },
    {
        "id": 70843921,
        "title": "千盏",
        "isCover": false,
        "date": "2019-10-11 13:59",
        "rank": 12,
        "point": 56645,
        "view": 15108,
        "favorite": 1562,
        "reply": 197,
        "danmaku": 93,
        "corrA": 0.74,
        "corrB": 25.85
    },
    {
        "id": 64107085,
        "title": "达拉崩吧·史诗版",
        "isCover": false,
        "date": "2019-08-17 17:47",
        "rank": 13,
        "point": 43723,
        "view": 30112,
        "favorite": 1646,
        "reply": 47,
        "danmaku": 93,
        "corrA": 0.92,
        "corrB": 13.67
    },
    {
        "id": 69902941,
        "title": "蔚蓝",
        "isCover": false,
        "date": "2019-10-04 18:00",
        "rank": 14,
        "point": 41220,
        "view": 6207,
        "favorite": 911,
        "reply": 80,
        "danmaku": 37,
        "corrA": 0.78,
        "corrB": 36.69
    },
    {
        "id": 70553582,
        "title": "雁门太守行",
        "isCover": false,
        "date": "2019-10-08 16:45",
        "rank": 15,
        "point": 38073,
        "view": 3170,
        "favorite": 664,
        "reply": 134,
        "danmaku": 127,
        "corrA": 0.49,
        "corrB": 50.0
    },
    {
        "id": 70056646,
        "title": "整合一战",
        "isCover": true,
        "date": "2019-10-04 19:12",
        "rank": 16,
        "point": 35883,
        "view": 7237,
        "favorite": 878,
        "reply": 105,
        "danmaku": 64,
        "corrA": 0.75,
        "corrB": 30.33
    },
    {
        "id": 70796250,
        "title": "午夜电台",
        "isCover": false,
        "date": "2019-10-11 03:30",
        "rank": 17,
        "point": 31519,
        "view": 1932,
        "favorite": 566,
        "reply": 90,
        "danmaku": 9,
        "corrA": 0.57,
        "corrB": 50.0
    },
    {
        "id": 69744969,
        "title": "邻家男孩",
        "isCover": false,
        "date": "2019-10-04 14:45",
        "rank": 18,
        "point": 30600,
        "view": 18164,
        "favorite": 1040,
        "reply": 72,
        "danmaku": 59,
        "corrA": 0.88,
        "corrB": 14.31
    },
    {
        "id": 2129461,
        "title": "普通DISCO",
        "isCover": false,
        "date": "2015-03-21 10:01",
        "rank": 19,
        "point": 30250,
        "view": 41033,
        "favorite": 850,
        "reply": 878,
        "danmaku": 207,
        "corrA": 0.57,
        "corrB": 5.18
    },
    {
        "id": 36570568,
        "title": "冠世一战",
        "isCover": false,
        "date": "2019-02-04 21:00",
        "rank": 20,
        "point": 29707,
        "view": 21818,
        "favorite": 581,
        "reply": 2433,
        "danmaku": 147,
        "corrA": 0.25,
        "corrB": 6.66
    },
    {
        "id": 70148346,
        "title": "遥醉吟",
        "isCover": false,
        "date": "2019-10-05 16:30",
        "rank": 21,
        "point": 29259,
        "view": 17181,
        "favorite": 939,
        "reply": 139,
        "danmaku": 78,
        "corrA": 0.8,
        "corrB": 13.66
    },
    {
        "id": 70342004,
        "title": "自我完结诊断",
        "isCover": false,
        "date": "2019-10-07 10:30",
        "rank": 22,
        "point": 28796,
        "view": 2336,
        "favorite": 506,
        "reply": 71,
        "danmaku": 10,
        "corrA": 0.65,
        "corrB": 50.0
    },
    {
        "id": 68074814,
        "title": "地铁三号线",
        "isCover": false,
        "date": "2019-09-19 18:00",
        "rank": 23,
        "point": 28412,
        "view": 7024,
        "favorite": 758,
        "reply": 42,
        "danmaku": 28,
        "corrA": 0.87,
        "corrB": 26.98
    },
    {
        "id": 69132126,
        "title": "这就是中国",
        "isCover": false,
        "date": "2019-09-27 17:18",
        "rank": 24,
        "point": 27537,
        "view": 15331,
        "favorite": 932,
        "reply": 26,
        "danmaku": 170,
        "corrA": 0.86,
        "corrB": 15.2
    },
    {
        "id": 58811214,
        "title": "洛水天依",
        "isCover": false,
        "date": "2019-07-12 17:04",
        "rank": 25,
        "point": 25036,
        "view": 8780,
        "favorite": 681,
        "reply": 172,
        "danmaku": 60,
        "corrA": 0.7,
        "corrB": 19.39
    },
    {
        "id": 70282946,
        "title": "词里有另一个我",
        "isCover": false,
        "date": "2019-10-06 17:00",
        "rank": 26,
        "point": 22905,
        "view": 3260,
        "favorite": 490,
        "reply": 68,
        "danmaku": 10,
        "corrA": 0.72,
        "corrB": 37.58
    },
    {
        "id": 17632970,
        "title": "天行健",
        "isCover": false,
        "date": "2017-12-26 08:57",
        "rank": 27,
        "point": 22900,
        "view": 14188,
        "favorite": 724,
        "reply": 70,
        "danmaku": 73,
        "corrA": 0.86,
        "corrB": 12.76
    },
    {
        "id": 70022241,
        "title": "掷千年",
        "isCover": true,
        "date": "2019-10-04 18:00",
        "rank": 28,
        "point": 20968,
        "view": 5000,
        "favorite": 548,
        "reply": 45,
        "danmaku": 23,
        "corrA": 0.83,
        "corrB": 27.4
    },
    {
        "id": 70577217,
        "title": "Born to do remix",
        "isCover": false,
        "date": "2019-10-08 21:42",
        "rank": 29,
        "point": 20749,
        "view": 1877,
        "favorite": 364,
        "reply": 92,
        "danmaku": 13,
        "corrA": 0.53,
        "corrB": 48.48
    },
    {
        "id": 69915934,
        "title": "依绫物语",
        "isCover": false,
        "date": "2019-10-04 18:30",
        "rank": 30,
        "point": 20476,
        "view": 2796,
        "favorite": 432,
        "reply": 58,
        "danmaku": 54,
        "corrA": 0.66,
        "corrB": 38.63
    },
    {
        "id": 70353482,
        "title": "幻想歌莺",
        "isCover": false,
        "date": "2019-10-06 21:26",
        "rank": 32,
        "point": 17955,
        "view": 1461,
        "favorite": 314,
        "reply": 54,
        "danmaku": 20,
        "corrA": 0.58,
        "corrB": 50.0
    },
    {
        "id": 69828170,
        "title": "海边的朝圣者",
        "isCover": false,
        "date": "2019-10-10 07:00",
        "rank": 35,
        "point": 13662,
        "view": 751,
        "favorite": 245,
        "reply": 64,
        "danmaku": 13,
        "corrA": 0.41,
        "corrB": 50.0
    },
    {
        "id": 70288312,
        "title": "诞月谣",
        "isCover": false,
        "date": "2019-10-06 18:58",
        "rank": 58,
        "point": 7789,
        "view": 559,
        "favorite": 136,
        "reply": 35,
        "danmaku": 3,
        "corrA": 0.49,
        "corrB": 50.0
    },
    {
        "id": 70839994,
        "title": "贪吃蛇",
        "isCover": false,
        "date": "2019-10-11 12:08",
        "rank": 106,
        "point": 2554,
        "view": 161,
        "favorite": 45,
        "reply": 11,
        "danmaku": 4,
        "corrA": 0.46,
        "corrB": 50.0
    },
    {
        "id": 70884075,
        "title": "那个日常",
        "isCover": false,
        "date": "2019-10-11 19:24",
        "rank": 197,
        "point": 2055,
        "view": 112,
        "favorite": 36,
        "reply": 26,
        "danmaku": 0,
        "corrA": 0.22,
        "corrB": 50.0
    }
]