[
    {
        "article": "普通DISCO",
        "danmaku": 2100,
        "danmakuWt": null,
        "date": "2015-03-21 10:01",
        "favorite": 2215,
        "favoriteWt": null,
        "id": "2129461",
        "isCover": false,
        "point": 89158,
        "rank": "SH",
        "reply": 344,
        "replyWt": null,
        "title": "普通DISCO",
        "view": 108232,
        "viewWt": null
    },
    {
        "article": "权御天下",
        "danmaku": 959,
        "danmakuWt": null,
        "date": "2015-03-05 00:32",
        "favorite": 1996,
        "favoriteWt": null,
        "id": "2075941",
        "isCover": false,
        "point": 75949,
        "rank": "SH",
        "reply": 323,
        "replyWt": null,
        "title": "权御天下",
        "view": 76313,
        "viewWt": null
    },
    {
        "article": "东京不太热",
        "danmaku": 14299,
        "danmakuWt": 0.63,
        "date": "2015-04-24 13:03",
        "favorite": 20869,
        "favoriteWt": 17.52,
        "id": "2251501",
        "isCover": false,
        "point": 716297,
        "rank": 1,
        "reply": 2469,
        "replyWt": 15.75,
        "title": "东京不太热",
        "view": 595554,
        "viewWt": null
    },
    {
        "article": "女孩你为何踮脚尖",
        "danmaku": 1261,
        "danmakuWt": 0.68,
        "date": "2015-04-18 13:53",
        "favorite": 3341,
        "favoriteWt": 28.43,
        "id": "2231891",
        "isCover": false,
        "point": 134808,
        "rank": 2,
        "reply": 270,
        "replyWt": 17.0,
        "title": "女孩你为何踮脚尖",
        "view": 58753,
        "viewWt": null
    },
    {
        "article": "呓语红尘",
        "danmaku": 1074,
        "danmakuWt": 0.5,
        "date": "2015-04-30 23:21",
        "favorite": 1462,
        "favoriteWt": 26.91,
        "id": "2273527",
        "isCover": false,
        "point": 64263,
        "rank": 3,
        "reply": 464,
        "replyWt": 12.5,
        "title": "呓语红尘",
        "view": 27168,
        "viewWt": null
    },
    {
        "article": "做一个默默无闻的普通人是一种怎样的体验",
        "danmaku": 1048,
        "danmakuWt": 0.72,
        "date": "2015-04-30 05:48",
        "favorite": 1209,
        "favoriteWt": 9.9,
        "id": "2270611",
        "isCover": false,
        "point": 51387,
        "rank": 4,
        "reply": 193,
        "replyWt": 18.0,
        "title": "做一个默默无闻的普通人是一种怎样的体验",
        "view": 61090,
        "viewWt": null
    },
    {
        "article": "阴阳先生",
        "danmaku": 392,
        "danmakuWt": 0.78,
        "date": "2015-02-08 00:04",
        "favorite": 622,
        "favoriteWt": 8.59,
        "id": "1971745",
        "isCover": false,
        "point": 28188,
        "rank": 5,
        "reply": 138,
        "replyWt": 19.5,
        "title": "阴阳先生",
        "view": 36213,
        "viewWt": null
    },
    {
        "article": "逐梦之翼",
        "danmaku": 859,
        "danmakuWt": 0.46,
        "date": "2014-07-03 11:10",
        "favorite": 501,
        "favoriteWt": 31.46,
        "id": "1251026",
        "isCover": false,
        "point": 24901,
        "rank": 6,
        "reply": 68,
        "replyWt": 11.5,
        "title": "逐梦之翼",
        "view": 7963,
        "viewWt": null
    },
    {
        "article": "八辈子",
        "danmaku": 764,
        "danmakuWt": 0.58,
        "date": "2014-07-03 09:19",
        "favorite": 559,
        "favoriteWt": 22.45,
        "id": "1250752",
        "isCover": false,
        "point": 24813,
        "rank": 7,
        "reply": 41,
        "replyWt": 14.5,
        "title": "八辈子",
        "view": 12452,
        "viewWt": null
    },
    {
        "article": "忆红莲",
        "danmaku": 169,
        "danmakuWt": 0.8,
        "date": "2013-08-29 01:39",
        "favorite": 467,
        "favoriteWt": 29.25,
        "id": "737481",
        "isCover": false,
        "point": 22238,
        "rank": 8,
        "reply": 23,
        "replyWt": 20.0,
        "title": "忆红莲",
        "view": 7984,
        "viewWt": null
    },
    {
        "article": "seventeen",
        "danmaku": 464,
        "danmakuWt": 0.48,
        "date": "2015-04-27 13:23",
        "favorite": 247,
        "favoriteWt": 10.53,
        "id": "2262626",
        "isCover": false,
        "point": 18233,
        "rank": 9,
        "reply": 379,
        "replyWt": 12.0,
        "title": "seventeen",
        "view": 11723,
        "viewWt": null
    },
    {
        "article": "一半一半",
        "danmaku": 163,
        "danmakuWt": 0.75,
        "date": "2013-02-22 16:07",
        "favorite": 357,
        "favoriteWt": 28.69,
        "id": "482844",
        "isCover": false,
        "point": 17073,
        "rank": 10,
        "reply": 26,
        "replyWt": 18.75,
        "title": "一半一半",
        "view": 6221,
        "viewWt": null
    },
    {
        "article": "视线",
        "danmaku": 437,
        "danmakuWt": 0.7,
        "date": "2015-04-03 19:37",
        "favorite": 281,
        "favoriteWt": 11.16,
        "id": "2173794",
        "isCover": true,
        "point": 15193,
        "rank": 11,
        "reply": 26,
        "replyWt": 17.5,
        "title": "视线",
        "view": 12594,
        "viewWt": null
    },
    {
        "article": "神经病之歌",
        "danmaku": 219,
        "danmakuWt": 0.84,
        "date": "2014-12-30 22:41",
        "favorite": 298,
        "favoriteWt": 8.3,
        "id": "1844227",
        "isCover": false,
        "point": 14736,
        "rank": 12,
        "reply": 23,
        "replyWt": 21.0,
        "title": "神经病之歌",
        "view": 17942,
        "viewWt": null
    },
    {
        "article": "陨星",
        "danmaku": 247,
        "danmakuWt": 0.75,
        "date": "2015-04-14 15:01",
        "favorite": 301,
        "favoriteWt": 17.22,
        "id": "2219151",
        "isCover": false,
        "point": 14613,
        "rank": 13,
        "reply": 27,
        "replyWt": 18.75,
        "title": "陨星",
        "view": 8739,
        "viewWt": null
    },
    {
        "article": "DOTA税",
        "danmaku": 106,
        "danmakuWt": 0.86,
        "date": "2014-02-10 19:26",
        "favorite": 258,
        "favoriteWt": 12.27,
        "id": "956683",
        "isCover": true,
        "point": 14179,
        "rank": 14,
        "reply": 31,
        "replyWt": 21.5,
        "title": "DOTA税",
        "view": 10512,
        "viewWt": null
    },
    {
        "article": "逃课税",
        "danmaku": 345,
        "danmakuWt": 0.73,
        "date": "2015-04-06 23:00",
        "favorite": 247,
        "favoriteWt": 11.6,
        "id": "2193152",
        "isCover": true,
        "point": 13788,
        "rank": 15,
        "reply": 19,
        "replyWt": 18.25,
        "title": "逃课税",
        "view": 10650,
        "viewWt": null
    },
    {
        "article": "一梦千朝",
        "danmaku": 125,
        "danmakuWt": 0.85,
        "date": "2015-01-10 09:50",
        "favorite": 293,
        "favoriteWt": 19.73,
        "id": "1874892",
        "isCover": false,
        "point": 13481,
        "rank": 16,
        "reply": 8,
        "replyWt": 21.25,
        "title": "一梦千朝",
        "view": 7424,
        "viewWt": null
    },
    {
        "article": "是萝莉控真是太好了",
        "danmaku": 606,
        "danmakuWt": 0.7,
        "date": "2015-04-24 22:12",
        "favorite": 283,
        "favoriteWt": 5.32,
        "id": "2253184",
        "isCover": true,
        "point": 13292,
        "rank": 17,
        "reply": 93,
        "replyWt": 17.5,
        "title": "是萝莉控真是太好了",
        "view": 26599,
        "viewWt": null
    },
    {
        "article": "枯干的画笔",
        "danmaku": 75,
        "danmakuWt": 0.71,
        "date": "2014-10-09 08:18",
        "favorite": 357,
        "favoriteWt": 20.44,
        "id": "1606010",
        "isCover": false,
        "point": 12800,
        "rank": 18,
        "reply": 61,
        "replyWt": 17.75,
        "title": "枯干的画笔",
        "view": 8735,
        "viewWt": null
    },
    {
        "article": "某个幽灵的愿望",
        "danmaku": 302,
        "danmakuWt": 0.49,
        "date": "2015-04-26 10:36",
        "favorite": 210,
        "favoriteWt": 15.42,
        "id": "2258423",
        "isCover": false,
        "point": 12779,
        "rank": 19,
        "reply": 211,
        "replyWt": 12.25,
        "title": "某个幽灵的愿望",
        "view": 6809,
        "viewWt": null
    },
    {
        "article": "紫苑镇",
        "danmaku": 295,
        "danmakuWt": 0.69,
        "date": "2015-04-26 15:32",
        "favorite": 191,
        "favoriteWt": 11.04,
        "id": "2259555",
        "isCover": false,
        "point": 11892,
        "rank": 20,
        "reply": 54,
        "replyWt": 17.25,
        "title": "紫苑镇",
        "view": 8649,
        "viewWt": null
    },
    {
        "article": "弥",
        "danmaku": 193,
        "danmakuWt": 0.72,
        "date": "2015-04-30 12:48",
        "favorite": 165,
        "favoriteWt": 11.71,
        "id": "2271249",
        "isCover": false,
        "point": 9870,
        "rank": 25,
        "reply": 42,
        "replyWt": 18.0,
        "title": "弥",
        "view": 7043,
        "viewWt": null
    },
    {
        "article": "解脱",
        "danmaku": 175,
        "danmakuWt": 0.62,
        "date": "2015-04-26 13:14",
        "favorite": 127,
        "favoriteWt": 12.88,
        "id": "2258956",
        "isCover": false,
        "point": 7727,
        "rank": 32,
        "reply": 68,
        "replyWt": 15.5,
        "title": "解脱",
        "view": 4929,
        "viewWt": null
    },
    {
        "article": "汝之神",
        "danmaku": 109,
        "danmakuWt": 0.56,
        "date": "2015-04-25 22:25",
        "favorite": 76,
        "favoriteWt": 16.99,
        "id": "2257136",
        "isCover": false,
        "point": 4107,
        "rank": 46,
        "reply": 37,
        "replyWt": 14.0,
        "title": "汝之神",
        "view": 2237,
        "viewWt": null
    },
    {
        "article": "Eternal Return",
        "danmaku": 56,
        "danmakuWt": 0.58,
        "date": "2015-04-26 21:03",
        "favorite": 55,
        "favoriteWt": 17.47,
        "id": "2260895",
        "isCover": false,
        "point": 3002,
        "rank": 61,
        "reply": 30,
        "replyWt": 14.5,
        "title": "Eternal Return",
        "view": 1574,
        "viewWt": null
    },
    {
        "article": "风萤月",
        "danmaku": 30,
        "danmakuWt": 0.49,
        "date": "2015-04-30 21:12",
        "favorite": 17,
        "favoriteWt": 6.88,
        "id": "2272943",
        "isCover": true,
        "point": 1594,
        "rank": 103,
        "reply": 50,
        "replyWt": 12.25,
        "title": "风萤月",
        "view": 1236,
        "viewWt": null
    }
]