[
    {
        "article": "遥远的相遇",
        "danmaku": 136,
        "danmakuWt": 0.66,
        "date": "2020-01-17 18:25",
        "favorite": 2648,
        "favoriteWt": 41.9,
        "id": "83828800",
        "isCover": false,
        "point": 129303,
        "rank": 1,
        "reply": 325,
        "replyWt": 16.5,
        "title": "遥远的相遇",
        "view": 15800,
        "viewWt": null
    },
    {
        "article": "惊天",
        "danmaku": 143,
        "danmakuWt": 0.84,
        "date": "2020-01-10 11:30",
        "favorite": 3370,
        "favoriteWt": 28.51,
        "id": "82430030",
        "isCover": false,
        "point": 119208,
        "rank": 2,
        "reply": 154,
        "replyWt": 21.0,
        "title": "惊天",
        "view": 29552,
        "viewWt": null
    },
    {
        "article": "七年之痒",
        "danmaku": 105,
        "danmakuWt": 0.81,
        "date": "2020-01-10 17:30",
        "favorite": 3057,
        "favoriteWt": 28.6,
        "id": "82813415",
        "isCover": false,
        "point": 109744,
        "rank": 3,
        "reply": 191,
        "replyWt": 20.2,
        "title": "七年之痒",
        "view": 26723,
        "viewWt": null
    },
    {
        "article": "若我突然死亡",
        "danmaku": 122,
        "danmakuWt": 0.76,
        "date": "2020-01-11 14:06",
        "favorite": 2510,
        "favoriteWt": 29.57,
        "id": "82948185",
        "isCover": false,
        "point": 94178,
        "rank": 4,
        "reply": 224,
        "replyWt": 19.0,
        "title": "若我突然死亡",
        "view": 21218,
        "viewWt": null
    },
    {
        "article": "冠世一战",
        "danmaku": 378,
        "danmakuWt": 0.51,
        "date": "2019-02-04 21:00",
        "favorite": 2712,
        "favoriteWt": 9.58,
        "id": "36570568",
        "isCover": false,
        "point": 88789,
        "rank": 5,
        "reply": 1877,
        "replyWt": 12.8,
        "title": "冠世一战",
        "view": 70760,
        "viewWt": null
    },
    {
        "article": "生僻字(V家)",
        "danmaku": 635,
        "danmakuWt": 0.8,
        "date": "2019-12-30 11:47",
        "favorite": 2971,
        "favoriteWt": 15.07,
        "id": "81248937",
        "isCover": true,
        "point": 76796,
        "rank": 6,
        "reply": 94,
        "replyWt": 20.0,
        "title": "化学生僻字",
        "view": 49272,
        "viewWt": null
    },
    {
        "article": "赤伶",
        "danmaku": 138,
        "danmakuWt": 0.7,
        "date": "2019-12-07 18:05",
        "favorite": 2918,
        "favoriteWt": 19.82,
        "id": "77889118",
        "isCover": true,
        "point": 70475,
        "rank": 7,
        "reply": 191,
        "replyWt": 17.5,
        "title": "赤伶",
        "view": 36810,
        "viewWt": null
    },
    {
        "article": "上山岗",
        "danmaku": 248,
        "danmakuWt": 0.74,
        "date": "2019-12-22 00:45",
        "favorite": 2454,
        "favoriteWt": 12.36,
        "id": "80155822",
        "isCover": false,
        "point": 68789,
        "rank": 8,
        "reply": 457,
        "replyWt": 18.5,
        "title": "上山岗",
        "view": 49640,
        "viewWt": null
    },
    {
        "article": "风华引",
        "danmaku": 140,
        "danmakuWt": 0.86,
        "date": "2020-01-01 10:00",
        "favorite": 2020,
        "favoriteWt": 24.14,
        "id": "81421041",
        "isCover": false,
        "point": 65804,
        "rank": 9,
        "reply": 68,
        "replyWt": 21.5,
        "title": "风华引",
        "view": 20918,
        "viewWt": null
    },
    {
        "article": "万神纪",
        "danmaku": 130,
        "danmakuWt": 0.77,
        "date": "2017-02-10 12:00",
        "favorite": 2069,
        "favoriteWt": 12.27,
        "id": "8506694",
        "isCover": false,
        "point": 58283,
        "rank": 10,
        "reply": 349,
        "replyWt": 19.2,
        "title": "万神纪",
        "view": 42158,
        "viewWt": null
    },
    {
        "article": "九九八十一(乐正绫)",
        "danmaku": 174,
        "danmakuWt": 0.87,
        "date": "2016-02-22 00:00",
        "favorite": 2173,
        "favoriteWt": 9.89,
        "id": "3905462",
        "isCover": false,
        "point": 57267,
        "rank": 11,
        "reply": 162,
        "replyWt": 21.8,
        "title": "九九八十一",
        "view": 54917,
        "viewWt": null
    },
    {
        "article": "冬已去，春未来2",
        "danmaku": 54,
        "danmakuWt": 0.67,
        "date": "2020-01-17 18:30",
        "favorite": 1366,
        "favoriteWt": 30.94,
        "id": "83805347",
        "isCover": false,
        "point": 57208,
        "rank": 12,
        "reply": 262,
        "replyWt": 16.8,
        "title": "冬已去，春未来2",
        "view": 11039,
        "viewWt": null
    },
    {
        "article": "God Rest Ye Merry Gentlemen",
        "danmaku": 44,
        "danmakuWt": 0.92,
        "date": "2019-12-25 12:25",
        "favorite": 1570,
        "favoriteWt": 25.86,
        "id": "80553734",
        "isCover": true,
        "point": 54217,
        "rank": 13,
        "reply": 43,
        "replyWt": 23.0,
        "title": "God Rest Ye Merry Gentlemen",
        "view": 15175,
        "viewWt": null
    },
    {
        "article": "好想爱这个世界啊",
        "danmaku": 82,
        "danmakuWt": 0.81,
        "date": "2020-01-10 12:00",
        "favorite": 1264,
        "favoriteWt": 33.72,
        "id": "82567592",
        "isCover": true,
        "point": 53779,
        "rank": 14,
        "reply": 85,
        "replyWt": 20.2,
        "title": "好想爱这个世界啊",
        "view": 9370,
        "viewWt": null
    },
    {
        "article": "勾指起誓",
        "danmaku": 234,
        "danmakuWt": 0.78,
        "date": "2019-02-13 22:09",
        "favorite": 1779,
        "favoriteWt": 9.59,
        "id": "43426592",
        "isCover": false,
        "point": 50245,
        "rank": 15,
        "reply": 306,
        "replyWt": 19.5,
        "title": "勾指起誓",
        "view": 46382,
        "viewWt": null
    },
    {
        "article": "三峡行舟调",
        "danmaku": 70,
        "danmakuWt": 0.61,
        "date": "2020-01-10 17:35",
        "favorite": 946,
        "favoriteWt": 43.08,
        "id": "82819088",
        "isCover": false,
        "point": 48878,
        "rank": 16,
        "reply": 170,
        "replyWt": 15.2,
        "title": "三峡行舟调",
        "view": 5490,
        "viewWt": null
    },
    {
        "article": "地势坤",
        "danmaku": 369,
        "danmakuWt": 0.81,
        "date": "2019-10-01 00:00",
        "favorite": 1884,
        "favoriteWt": 7.87,
        "id": "69519887",
        "isCover": false,
        "point": 47673,
        "rank": 17,
        "reply": 250,
        "replyWt": 20.2,
        "title": "地势坤",
        "view": 59848,
        "viewWt": null
    },
    {
        "article": "Final⇆Endless",
        "danmaku": 62,
        "danmakuWt": 0.9,
        "date": "2020-01-09 23:55",
        "favorite": 1637,
        "favoriteWt": 16.79,
        "id": "82726690",
        "isCover": false,
        "point": 46323,
        "rank": 18,
        "reply": 71,
        "replyWt": 22.5,
        "title": "Final⇆Endless",
        "view": 24369,
        "viewWt": null
    },
    {
        "article": "白日妄想",
        "danmaku": 110,
        "danmakuWt": 0.55,
        "date": "2020-01-17 19:10",
        "favorite": 800,
        "favoriteWt": 50.0,
        "id": "83814093",
        "isCover": false,
        "point": 44923,
        "rank": 19,
        "reply": 113,
        "replyWt": 13.8,
        "title": "白日妄想",
        "view": 3309,
        "viewWt": null
    },
    {
        "article": "勿忘草(乐正绫)",
        "danmaku": 47,
        "danmakuWt": 0.78,
        "date": "2020-01-10 12:30",
        "favorite": 1060,
        "favoriteWt": 29.01,
        "id": "82373267",
        "isCover": false,
        "point": 42242,
        "rank": 20,
        "reply": 119,
        "replyWt": 19.5,
        "title": "勿忘草",
        "view": 9135,
        "viewWt": null
    },
    {
        "article": "权御天下",
        "danmaku": 111,
        "danmakuWt": 0.87,
        "date": "2015-03-05 00:32",
        "favorite": 1338,
        "favoriteWt": 9.97,
        "id": "2075941",
        "isCover": false,
        "point": 37562,
        "rank": 21,
        "reply": 111,
        "replyWt": 21.8,
        "title": "权御天下",
        "view": 33554,
        "viewWt": null
    },
    {
        "article": "龙炎图",
        "danmaku": 64,
        "danmakuWt": 0.82,
        "date": "2020-01-04 20:53",
        "favorite": 962,
        "favoriteWt": 26.56,
        "id": "82066462",
        "isCover": false,
        "point": 36195,
        "rank": 22,
        "reply": 75,
        "replyWt": 20.5,
        "title": "龙炎图",
        "view": 9055,
        "viewWt": null
    },
    {
        "article": "一点一点",
        "danmaku": 177,
        "danmakuWt": 0.81,
        "date": "2019-12-25 12:25",
        "favorite": 1207,
        "favoriteWt": 13.08,
        "id": "80433773",
        "isCover": false,
        "point": 34833,
        "rank": 23,
        "reply": 117,
        "replyWt": 20.2,
        "title": "一点一点",
        "view": 23067,
        "viewWt": null
    },
    {
        "article": "日记(V家)",
        "danmaku": 35,
        "danmakuWt": 0.5,
        "date": "2020-01-12 12:00",
        "favorite": 721,
        "favoriteWt": 34.98,
        "id": "83022080",
        "isCover": false,
        "point": 33791,
        "rank": 24,
        "reply": 272,
        "replyWt": 12.5,
        "title": "日记",
        "view": 5153,
        "viewWt": null
    },
    {
        "article": "逆浪千秋",
        "danmaku": 81,
        "danmakuWt": 0.86,
        "date": "2018-03-01 12:00",
        "favorite": 1163,
        "favoriteWt": 11.44,
        "id": "20204904",
        "isCover": false,
        "point": 33400,
        "rank": 25,
        "reply": 108,
        "replyWt": 21.5,
        "title": "逆浪千秋",
        "view": 25409,
        "viewWt": null
    },
    {
        "article": "草生人间",
        "danmaku": 36,
        "danmakuWt": 0.73,
        "date": "2019-12-28 15:38",
        "favorite": 598,
        "favoriteWt": 38.3,
        "id": "80971253",
        "isCover": false,
        "point": 28055,
        "rank": 26,
        "reply": 67,
        "replyWt": 18.2,
        "title": "草生人间",
        "view": 3903,
        "viewWt": null
    },
    {
        "article": "剑器行",
        "danmaku": 27,
        "danmakuWt": 0.88,
        "date": "2019-12-15 18:00",
        "favorite": 707,
        "favoriteWt": 21.8,
        "id": "79346870",
        "isCover": false,
        "point": 24534,
        "rank": 27,
        "reply": 45,
        "replyWt": 22.0,
        "title": "剑器行",
        "view": 8108,
        "viewWt": null
    },
    {
        "article": "大氿歌",
        "danmaku": 24,
        "danmakuWt": 0.94,
        "date": "2019-03-01 20:30",
        "favorite": 812,
        "favoriteWt": 10.54,
        "id": "45020985",
        "isCover": false,
        "point": 24100,
        "rank": 28,
        "reply": 38,
        "replyWt": 23.5,
        "title": "大氿歌",
        "view": 19253,
        "viewWt": null
    },
    {
        "article": "繁华唱遍",
        "danmaku": 29,
        "danmakuWt": 0.86,
        "date": "2019-02-04 21:00",
        "favorite": 718,
        "favoriteWt": 9.8,
        "id": "36570707",
        "isCover": false,
        "point": 23131,
        "rank": 29,
        "reply": 102,
        "replyWt": 21.5,
        "title": "繁华唱遍",
        "view": 18320,
        "viewWt": null
    },
    {
        "article": "绝体绝命(洛天依)",
        "danmaku": 91,
        "danmakuWt": 0.87,
        "date": "2018-04-04 00:00",
        "favorite": 712,
        "favoriteWt": 13.62,
        "id": "21551703",
        "isCover": false,
        "point": 22356,
        "rank": 30,
        "reply": 48,
        "replyWt": 21.8,
        "title": "绝体绝命",
        "view": 13071,
        "viewWt": null
    },
    {
        "article": "镜中水雾",
        "danmaku": 31,
        "danmakuWt": 0.29,
        "date": "2020-01-17 18:00",
        "favorite": 159,
        "favoriteWt": 50.0,
        "id": "83557270",
        "isCover": false,
        "point": 8941,
        "rank": 62,
        "reply": 65,
        "replyWt": 7.2,
        "title": "镜中水雾",
        "view": 511,
        "viewWt": null
    },
    {
        "article": "东方年兽记",
        "danmaku": 0,
        "danmakuWt": 0.5,
        "date": "2020-01-17 18:00",
        "favorite": 120,
        "favoriteWt": 50.0,
        "id": "83803352",
        "isCover": false,
        "point": 6693,
        "rank": 83,
        "reply": 25,
        "replyWt": 12.5,
        "title": "东方年兽记",
        "view": 381,
        "viewWt": null
    },
    {
        "article": "请继续开心走",
        "danmaku": 7,
        "danmakuWt": 0.34,
        "date": "2020-01-17 12:00",
        "favorite": 80,
        "favoriteWt": 50.0,
        "id": "83695057",
        "isCover": false,
        "point": 4496,
        "rank": 124,
        "reply": 29,
        "replyWt": 8.5,
        "title": "请继续开心走",
        "view": 248,
        "viewWt": null
    }
]