[
    {
        "article": "指引星",
        "danmaku": 59,
        "danmakuWt": 0.79,
        "date": "2021-02-27 20:00",
        "favorite": 3251,
        "favoriteWt": 30.5,
        "id": "929438561",
        "isCover": true,
        "point": 122501,
        "rank": 1,
        "reply": 252,
        "replyWt": 19.8,
        "title": "指引星",
        "view": 26644,
        "viewWt": null
    },
    {
        "article": "停下吧，时间",
        "danmaku": 92,
        "danmakuWt": 0.74,
        "date": "2021-02-27 14:18",
        "favorite": 3020,
        "favoriteWt": 32.14,
        "id": "671978395",
        "isCover": false,
        "point": 119316,
        "rank": 2,
        "reply": 294,
        "replyWt": 18.5,
        "title": "停下吧，时间",
        "view": 23494,
        "viewWt": null
    },
    {
        "article": "洗脑日记",
        "danmaku": 52,
        "danmakuWt": 0.93,
        "date": "2021-02-22 17:00",
        "favorite": 3298,
        "favoriteWt": 13.87,
        "id": "799277283",
        "isCover": false,
        "point": 83392,
        "rank": 3,
        "reply": 124,
        "replyWt": 23.2,
        "title": "洗脑日记",
        "view": 59436,
        "viewWt": null
    },
    {
        "article": "不认真主义宣言",
        "danmaku": 91,
        "danmakuWt": 0.56,
        "date": "2021-02-27 11:00",
        "favorite": 1445,
        "favoriteWt": 49.24,
        "id": "971967115",
        "isCover": false,
        "point": 82724,
        "rank": 4,
        "reply": 299,
        "replyWt": 14.0,
        "title": "不认真主义宣言",
        "view": 7336,
        "viewWt": null
    },
    {
        "article": "我亲爱的母亲",
        "danmaku": 81,
        "danmakuWt": 0.88,
        "date": "2021-02-01 11:30",
        "favorite": 122,
        "favoriteWt": 20.68,
        "id": "288933038",
        "isCover": false,
        "point": 80154,
        "rank": 5,
        "reply": 122,
        "replyWt": 22.0,
        "title": "我亲爱的母亲",
        "view": 32755,
        "viewWt": null
    },
    {
        "article": "列车正在行驶",
        "danmaku": 14,
        "danmakuWt": 0.94,
        "date": "2021-02-06 00:00",
        "favorite": 1934,
        "favoriteWt": 29.84,
        "id": "971432719",
        "isCover": false,
        "point": 71835,
        "rank": 6,
        "reply": 43,
        "replyWt": 23.5,
        "title": "列车正在行驶",
        "view": 16203,
        "viewWt": null
    },
    {
        "article": "非玩家角色(歌曲)",
        "danmaku": 15,
        "danmakuWt": 0.84,
        "date": "2021-02-13 19:00",
        "favorite": 1623,
        "favoriteWt": 28.9,
        "id": "714200363",
        "isCover": false,
        "point": 61416,
        "rank": 7,
        "reply": 118,
        "replyWt": 21.0,
        "title": "非玩家角色",
        "view": 14042,
        "viewWt": null
    },
    {
        "article": "中国节",
        "danmaku": 59,
        "danmakuWt": 0.9,
        "date": "2021-02-17 17:30",
        "favorite": 1882,
        "favoriteWt": 16.19,
        "id": "801664537",
        "isCover": false,
        "point": 52188,
        "rank": 8,
        "reply": 95,
        "replyWt": 22.5,
        "title": "中国节",
        "view": 29056,
        "viewWt": null
    },
    {
        "article": "银河纪行",
        "danmaku": 11,
        "danmakuWt": 0.6,
        "date": "2019-03-03 10:00",
        "favorite": 812,
        "favoriteWt": 50.0,
        "id": "756975259",
        "isCover": false,
        "point": 46055,
        "rank": 9,
        "reply": 136,
        "replyWt": 15.0,
        "title": "银河纪行",
        "view": 3409,
        "viewWt": null
    },
    {
        "article": "白噪音",
        "danmaku": 26,
        "danmakuWt": 0.91,
        "date": "2021-02-26 10:30",
        "favorite": 1246,
        "favoriteWt": 21.92,
        "id": "501840321",
        "isCover": true,
        "point": 40739,
        "rank": 10,
        "reply": 57,
        "replyWt": 22.8,
        "title": "白噪音",
        "view": 14214,
        "viewWt": null
    },
    {
        "article": "忘年辞",
        "danmaku": 13,
        "danmakuWt": 0.63,
        "date": "2020-02-27 02:01",
        "favorite": 557,
        "favoriteWt": 50.0,
        "id": "544392700",
        "isCover": false,
        "point": 34858,
        "rank": 11,
        "reply": 86,
        "replyWt": 15.8,
        "title": "忘年辞",
        "view": 2646,
        "viewWt": null
    },
    {
        "article": "勾指起誓",
        "danmaku": 81,
        "danmakuWt": 0.93,
        "date": "2019-02-13 22:09",
        "favorite": 1382,
        "favoriteWt": 6.53,
        "id": "43426592",
        "isCover": false,
        "point": 31683,
        "rank": 12,
        "reply": 88,
        "replyWt": 23.2,
        "title": "勾指起誓",
        "view": 52902,
        "viewWt": null
    },
    {
        "article": "小 王 子 病 毒",
        "danmaku": 7,
        "danmakuWt": 0.77,
        "date": "2021-02-26 17:00",
        "favorite": 516,
        "favoriteWt": 46.45,
        "id": "586804237",
        "isCover": false,
        "point": 27655,
        "rank": 13,
        "reply": 47,
        "replyWt": 19.2,
        "title": "小 王 子 病 毒",
        "view": 2777,
        "viewWt": null
    },
    {
        "article": "姐就是女王",
        "danmaku": 53,
        "danmakuWt": 0.89,
        "date": "2021-02-05 17:09",
        "favorite": 980,
        "favoriteWt": 8.57,
        "id": "331573716",
        "isCover": true,
        "point": 27277,
        "rank": 14,
        "reply": 103,
        "replyWt": 22.2,
        "title": "姐就是女王",
        "view": 28599,
        "viewWt": null
    },
    {
        "article": "未尽",
        "danmaku": 12,
        "danmakuWt": 0.49,
        "date": "2021-03-03 15:00",
        "favorite": 423,
        "favoriteWt": 50.0,
        "id": "586988495",
        "isCover": false,
        "point": 23801,
        "rank": 15,
        "reply": 93,
        "replyWt": 12.2,
        "title": "未尽",
        "view": 1506,
        "viewWt": null
    },
    {
        "article": "梦化鲤",
        "danmaku": 32,
        "danmakuWt": 0.7,
        "date": "2021-02-26 18:00",
        "favorite": 499,
        "favoriteWt": 38.18,
        "id": "331791169",
        "isCover": false,
        "point": 23461,
        "rank": 16,
        "reply": 64,
        "replyWt": 17.5,
        "title": "梦化鲤",
        "view": 3267,
        "viewWt": null
    },
    {
        "article": "谁是我的新郎",
        "danmaku": 155,
        "danmakuWt": 0.71,
        "date": "2021-02-26 17:10",
        "favorite": 595,
        "favoriteWt": 10.14,
        "id": "629418360",
        "isCover": true,
        "point": 44355,
        "rank": 17,
        "reply": 190,
        "replyWt": 17.8,
        "title": "谁是我的新郎",
        "view": 14673,
        "viewWt": null
    },
    {
        "article": "万象霜天",
        "danmaku": 18,
        "danmakuWt": 0.93,
        "date": "2021-02-12 22:43",
        "favorite": 703,
        "favoriteWt": 10.94,
        "id": "844213962",
        "isCover": true,
        "point": 21765,
        "rank": 18,
        "reply": 44,
        "replyWt": 23.2,
        "title": "万象霜天",
        "view": 16069,
        "viewWt": null
    },
    {
        "article": "写着模棱两可的歌",
        "danmaku": 4,
        "danmakuWt": 0.77,
        "date": "2021-02-20 18:30",
        "favorite": 496,
        "favoriteWt": 34.11,
        "id": "204250865",
        "isCover": false,
        "point": 21711,
        "rank": 19,
        "reply": 60,
        "replyWt": 19.2,
        "title": "写着模棱两可的歌",
        "view": 3635,
        "viewWt": null
    },
    {
        "article": "临别之语Ⅱ",
        "danmaku": 5,
        "danmakuWt": 0.57,
        "date": "2021-03-02 17:55",
        "favorite": 374,
        "favoriteWt": 50.0,
        "id": "801961274",
        "isCover": false,
        "point": 21152,
        "rank": 20,
        "reply": 68,
        "replyWt": 14.2,
        "title": "临别之语Ⅱ",
        "view": 1481,
        "viewWt": null
    },
    {
        "article": "积雪",
        "danmaku": 15,
        "danmakuWt": 0.93,
        "date": "2021-02-27 15:00",
        "favorite": 578,
        "favoriteWt": 16.82,
        "id": "844137885",
        "isCover": false,
        "point": 18909,
        "rank": 21,
        "reply": 25,
        "replyWt": 23.2,
        "title": "积雪",
        "view": 8592,
        "viewWt": null
    },
    {
        "article": "然而我不是神",
        "danmaku": 13,
        "danmakuWt": 0.93,
        "date": "2021-02-05 17:16",
        "favorite": 687,
        "favoriteWt": 6.37,
        "id": "799111882",
        "isCover": false,
        "point": 17598,
        "rank": 22,
        "reply": 62,
        "replyWt": 23.2,
        "title": "然而我不是神",
        "view": 26951,
        "viewWt": null
    },
    {
        "article": "我要控诉你谋杀",
        "danmaku": 20,
        "danmakuWt": 0.94,
        "date": "2020-07-29 16:30",
        "favorite": 496,
        "favoriteWt": 20.65,
        "id": "584033746",
        "isCover": true,
        "point": 16478,
        "rank": 23,
        "reply": 9,
        "replyWt": 23.5,
        "title": "我要控诉你谋杀",
        "view": 6006,
        "viewWt": null
    },
    {
        "article": "墨纸鸢",
        "danmaku": 21,
        "danmakuWt": 0.88,
        "date": "2021-02-10 19:00",
        "favorite": 485,
        "favoriteWt": 15.56,
        "id": "BV1W54y1W7Pb",
        "isCover": false,
        "point": 16413,
        "rank": 24,
        "reply": 48,
        "replyWt": 22.0,
        "title": "墨纸鸢",
        "view": 7792,
        "viewWt": null
    },
    {
        "article": "蝶云",
        "danmaku": 14,
        "danmakuWt": 0.91,
        "date": "2021-02-04 19:00",
        "favorite": 447,
        "favoriteWt": 25.67,
        "id": "801525854",
        "isCover": false,
        "point": 16204,
        "rank": 25,
        "reply": 16,
        "replyWt": 22.8,
        "title": "蝶云",
        "view": 4353,
        "viewWt": null
    },
    {
        "article": "万古生香",
        "danmaku": 54,
        "danmakuWt": 0.84,
        "date": "2020-01-24 22:54",
        "favorite": 584,
        "favoriteWt": 4.15,
        "id": "78977256",
        "isCover": false,
        "point": 15857,
        "rank": 26,
        "reply": 191,
        "replyWt": 21.0,
        "title": "万古生香",
        "view": 35191,
        "viewWt": null
    },
    {
        "article": "我的悲伤是水做的",
        "danmaku": 28,
        "danmakuWt": 0.94,
        "date": "2020-04-10 18:10",
        "favorite": 438,
        "favoriteWt": 10.35,
        "id": "285205499",
        "isCover": false,
        "point": 15296,
        "rank": 27,
        "reply": 19,
        "replyWt": 23.5,
        "title": "我的悲伤是水做的",
        "view": 10581,
        "viewWt": null
    },
    {
        "article": "花灵记",
        "danmaku": 5,
        "danmakuWt": 0.75,
        "date": "2021-02-15 12:05",
        "favorite": 296,
        "favoriteWt": 43.22,
        "id": "289184270",
        "isCover": false,
        "point": 15090,
        "rank": 28,
        "reply": 31,
        "replyWt": 18.8,
        "title": "花灵记",
        "view": 1712,
        "viewWt": null
    },
    {
        "article": "肮脏的神",
        "danmaku": 67,
        "danmakuWt": 0.69,
        "date": "2020-04-21 20:00",
        "favorite": 360,
        "favoriteWt": 10.9,
        "id": "667873249",
        "isCover": false,
        "point": 14920,
        "rank": 29,
        "reply": 156,
        "replyWt": 17.2,
        "title": "肮脏的神",
        "view": 8259,
        "viewWt": null
    },
    {
        "article": "燃尽微光",
        "danmaku": 17,
        "danmakuWt": 0.83,
        "date": "2021-02-15 12:00",
        "favorite": 343,
        "favoriteWt": 33.71,
        "id": "501731106",
        "isCover": false,
        "point": 14556,
        "rank": 30,
        "reply": 21,
        "replyWt": 20.8,
        "title": "燃尽微光",
        "view": 2544,
        "viewWt": null
    },
    {
        "article": "都铎王朝",
        "danmaku": 11,
        "danmakuWt": 0.36,
        "date": "2021-03-05 18:30",
        "favorite": 125,
        "favoriteWt": 50.0,
        "id": "BV1UZ4y1A7Z7",
        "isCover": false,
        "point": 6960,
        "rank": 67,
        "reply": 38,
        "replyWt": 9.0,
        "title": "都铎王朝",
        "view": 365,
        "viewWt": null
    },
    {
        "article": "Abyss",
        "danmaku": 4,
        "danmakuWt": 0.27,
        "date": "2021-02-27 09:00",
        "favorite": 33,
        "favoriteWt": 50.0,
        "id": "BV13K4y1D7V9",
        "isCover": false,
        "point": 1960,
        "rank": 209,
        "reply": 23,
        "replyWt": 6.8,
        "title": "Abyss",
        "view": 154,
        "viewWt": null
    },
    {
        "article": "春天的微风",
        "danmaku": 0,
        "danmakuWt": 0.3,
        "date": "2021-03-05 18:08",
        "favorite": 27,
        "favoriteWt": 50.0,
        "id": "BV1sy4y17799",
        "isCover": false,
        "point": 1518,
        "rank": 263,
        "reply": 12,
        "replyWt": 7.5,
        "title": "春天的微风",
        "view": 78,
        "viewWt": null
    },
    {
        "article": "阵雨",
        "danmaku": 1,
        "danmakuWt": 0.32,
        "date": "2021-03-04 02:43",
        "favorite": 11,
        "favoriteWt": 50.0,
        "id": "BV1RU4y1H7vy",
        "isCover": false,
        "point": 631,
        "rank": 539,
        "reply": 5,
        "replyWt": 8.0,
        "title": "阵雨",
        "view": 41,
        "viewWt": null
    }
]